Workbook

Sheet Ringkasan & Insight
B2: ANALISIS ONLINE RETAIL DATASET (Des 2010 - Des 2011)
B3: UK-based online retailer - giftware & household items
B5: KPI UTAMA (Data Bersih, setelah exclude cancelled/adjustment)
B7: Total Revenue (GBP) | D7: 10259030
B8: Jumlah Order (distinct invoice) | D8: 19776
B9: Rata-rata Order Value / AOV (GBP) | D9: =D7/D8 -> 518.76164
B10: Jumlah Customer Unik | D10: 4334 | E10: exclude baris CustomerID kosong
B11: Jumlah Produk Unik (StockCode) | D11: 3914
B12: Jumlah Negara | D12: 38
B13: Periode Data | D13: 1 Des 2010 - 9 Des 2011 (Des 2011 TIDAK penuh sebulan)
B14: Revenue Hilang akibat Cancelled Order (GBP) | D14: 893979.73
B15: % Order yang Dibatalkan | D15: 0.017394918
B17: INSIGHT UTAMA
B18: 1. Konsentrasi pasar sangat tinggi di United Kingdom (sekitar 85% dari total revenue). Ekspansi/marketing di negara Eropa lain (Belanda, Irlandia, Jerman, Prancis) berpotensi jadi peluang pertumbuhan karena kontribusinya masih kecil relatif ke ukuran pasarnya.
B20: 2. Revenue naik tajam di Sep-Nov 2011 (puncak November, sekitar GBP 1,45 juta) - pola musiman jelang Natal. Desember 2011 di data ini hanya sampai tanggal 9, jadi angkanya TIDAK mencerminkan bulan penuh - jangan dibaca sebagai penurunan performa.
B22: 3. Toko TIDAK memiliki transaksi sama sekali di hari Sabtu (kemungkinan toko/gudang tutup weekend hari itu). Jam paling ramai adalah 10:00-15:00 - waktu ini ideal untuk promosi/live campaign.
B24: 4. Distribusi revenue customer sangat timpang (prinsip Pareto): top 20% customer (866 orang) menyumbang 74.6% revenue, dan hanya 1133 customer (26.1% dari total) sudah menyumbang 80% revenue. Retensi/loyalty program ke segmen kecil ini berdampak besar.
B26: 5. Produk 'PAPER CRAFT, LITTLE BIRDIE' (StockCode 23843) masuk 15 besar revenue karena SATU transaksi outlier: Invoice 581483, qty 80,995 unit @GBP2.08 oleh customer 16446. Angka ini kemungkinan pembelian grosir/wholesale, bukan pola beli ritel biasa - sebaiknya di-exclude dari analisis 'produk terlaris ritel' agar tidak menyesatkan.
B28: 6. 25% baris transaksi bersih tidak punya CustomerID (kemungkinan transaksi guest/tanpa akun). Ini valid untuk analisis revenue & produk, tapi HARUS dikeluarkan dari analisis customer/RFM (sudah dilakukan di sheet Pivot_Customer).
B30: 7. Cancelled order membuat kehilangan potensi revenue sekitar GBP 893,980 (1.7% dari order). Perlu digali lebih lanjut alasan pembatalan (stok habis? kualitas? kesalahan input?) - data ini tidak punya kolom alasan cancel, jadi butuh data tambahan dari tim CS/ops.
B33: REKOMENDASI BISNIS
B34: - Fokuskan budget marketing/ads untuk retensi ke top ~20% customer (lihat sheet Pivot_Customer) lewat program loyalty/exclusive discount - dampak revenue-nya jauh lebih besar dibanding akuisisi customer baru secara acak.
B35: - Siapkan stok & tenaga tambahan untuk periode Sep-Nov menjelang Natal; pertimbangkan pre-order/early bird campaign di Agustus untuk smoothing lonjakan permintaan.
B36: - Investigasi akar penyebab cancelled order (sekitar 1.7% dari order, senilai sekitar GBP 894rb) - kalau bisa diturunkan setengahnya saja, itu revenue tambahan signifikan tanpa perlu akuisisi customer baru.
... B38: - Dorong customer guest (tanpa CustomerID, 25% transaksi) untuk membuat akun - supaya bisa masuk program loyalty & data historinya bisa dianalisis untuk personalisasi.

Sheet Dashboard
B2: DASHBOARD - ONLINE RETAIL ANALYSIS
B4: UK-based online retailer (giftware & household items) · Periode: Des 2010 – Des 2011 (Des 2011 tidak penuh sebulan)
B6: TOTAL REVENUE (GBP) | D6: JUMLAH ORDER | F6: AOV (GBP) | H6: CUSTOMER UNIK | J6: PRODUK UNIK | L6: NEGARA | N6: % ORDER DIBATALKAN
B7: ='Ringkasan & Insight'!D7 -> 10259030 | D7: ='Ringkasan & Insight'!D8 -> 19776 | F7: ='Ringkasan & Insight'!D9 -> 518.76164 | H7: ='Ringkasan & Insight'!D10 -> 4334 | J7: ='Ringkasan & Insight'!D11 -> 3914 | L7: ='Ringkasan & Insight'!D12 -> 38 | N7: ='Ringkasan & Insight'!D15 -> 0.017394918
Y12: Row Labels | Z12: Revenue
Y13: 2010-12 | Z13: 775714.95
Y14: 2011-01 | Z14: 670439.46
Y15: 2011-02 | Z15: 507866.54
Y16: 2011-03 | Z16: 689841.84
Y17: 2011-04 | Z17: 515499.66
Y18: 2011-05 | Z18: 740036.33
Y19: 2011-06 | Z19: 737683.99
Y20: 2011-07 | Z20: 688252.67
Y21: 2011-08 | Z21: 735370.22
Y22: 2011-09 | Z22: 1028345.4
Y23: 2011-10 | Z23: 1103364
Y24: 2011-11 | Z24: 1452116
... Y26: Grand Total | Z26: 10259030
Y28: Row Labels | Z28: Sum of Revenue (GBP)
Y29: CHILLI LIGHTS | Z29: 54096.36
Y30: ASSORTED COLOUR BIRD ORNAMENT | Z30: 58927.62
Y31: PAPER CHAIN KIT 50'S CHRISTMAS | Z31: 64875.59
Y32: RABBIT NIGHT LIGHT | Z32: 66870.03
Y33: MEDIUM CERAMIC TOP STORAGE JAR | Z33: 81700.92
Y34: JUMBO BAG RED RETROSPOT | Z34: 94159.81
Y35: PARTY BUNTING | Z35: 99445.23
Y36: WHITE HANGING HEART T-LIGHT HOLDER | Z36: 104284.24
Y37: PAPER CRAFT , LITTLE BIRDIE | Z37: 168469.6
Y38: REGENCY CAKESTAND 3 TIER | Z38: 174156.54
Y39: Grand Total | Z39: 966985.94
Y42: Row Labels | Z42: Revenue
Y43: 16029 | Z43: 72708.09
Y44: 12346 | Z44: 77183.6
Y45: 17511 | Z45: 91062.38
Y46: 14156 | Z46: 116560.08
Y47: 12415 | Z47: 124564.53
Y48: 14911 | Z48: 136161.83
Y49: 16446 | Z49: 168472.5
Y50: 17450 | Z50: 194390.79
Y51: 18102 | Z51: 259657.3
Y52: 14646 | Z52: 279138.02
Y53: Grand Total | Z53: 1519899.1

Sheet Log_Pembersihan_Data
B2: LOG PEMBERSIHAN DATA (Data Cleaning Log)
B4: # | C4: Langkah Cleaning | D4: Alasan | E4: Baris Terdampak | F4: Baris Tersisa
B5: 1 | C5: Hapus baris duplikat exact | D5: Mencegah pencatatan ganda (double-entry) pada transaksi yang identik | E5: 5268 | F5: 536641
B6: 2 | C6: Pemisahan transaksi batal (Invoice prefix "C") | D6: Bukan penjualan riil; dianalisis terpisah di sheet Data_Cancelled utk cancellation rate | E6: 9251 | F6: 527390
B7: 3 | C7: Filter UnitPrice <= 0 | D7: Mengeliminasi data stock adjustment & write-off internal | E7: 2512 | F7: 524878
B8: 4 | C8: Filter Quantity <= 0 | D8: Mengeliminasi transaksi anomali dengan jumlah nol atau negatif | E8: 0 | F8: 524878
B9: 5 | C9: Filter kode administratif / non-produk | D9: Mengeluarkan kode biaya operasional (POST, DOT, BANK CHARGES, AMAZONFEE, dll.) | E9: 2307 | F9: 522571
B11: HASIL AKHIR: 522.571 baris siap dipakai untuk analisis penjualan (basis perhitungan seluruh pivot di workbook ini)
B12: + 9.251 baris cancelled disimpan terpisah (sheet Data_Cancelled) untuk analisis pembatalan

Sheet Data_Cleaned
A1: InvoiceNo | B1: StockCode | C1: Description | D1: Quantity | E1: InvoiceDate | F1: UnitPrice | G1: CustomerID | H1: Country | I1: TotalPrice | J1: YearMonth
A2: 536365 | B2: 21730 | C2: GLASS STAR FROSTED T-LIGHT HOLDER | D2: 6 | E2: 40513.351 | F2: 4.25 | G2: 17850 | H2: United Kingdom | I2: 25.5 | J2: 2010-12
A3: 536370 | B3: 10002 | C3: INFLATABLE POLITICAL GLOBE | D3: 48 | E3: 40513.365 | F3: 0.85 | G3: 12583 | H3: France | I3: 40.8 | J3: 2010-12
A4: 536373 | B4: 21871 | C4: SAVE THE PLANET MUG | D4: 6 | E4: 40513.376 | F4: 1.06 | G4: 17850 | H4: United Kingdom | I4: 6.36 | J4: 2010-12
A5: 536376 | B5: 22114 | C5: HOT WATER BOTTLE TEA AND SYMPATHY | D5: 48 | E5: 40513.397 | F5: 3.45 | G5: 15291 | H5: United Kingdom | I5: 165.6 | J5: 2010-12
A6: 536378 | B6: 21931 | C6: JUMBO STORAGE BAG SUKI | D6: 10 | E6: 40513.401 | F6: 1.95 | G6: 14688 | H6: United Kingdom | I6: 19.5 | J6: 2010-12
A7: 536378 | B7: 20723 | C7: STRAWBERRY CHARLOTTE BAG | D7: 10 | E7: 40513.401 | F7: 0.85 | G7: 14688 | H7: United Kingdom | I7: 8.5 | J7: 2010-12
A8: 536378 | B8: 85183B | C8: CHARLIE & LOLA WASTEPAPER BIN FLORA | D8: 48 | E8: 40513.401 | F8: 1.25 | G8: 14688 | H8: United Kingdom | I8: 60 | J8: 2010-12
A9: 536381 | B9: 21166 | C9: COOK WITH WINE METAL SIGN | D9: 1 | E9: 40513.403 | F9: 1.95 | G9: 15311 | H9: United Kingdom | I9: 1.95 | J9: 2010-12
A10: 536381 | B10: 84971S | C10: SMALL HEART FLOWERS HOOK | D10: 6 | E10: 40513.403 | F10: 0.85 | G10: 15311 | H10: United Kingdom | I10: 5.1 | J10: 2010-12
A11: 536381 | B11: 21557 | C11: SET OF 6 FUNKY BEAKERS | D11: 2 | E11: 40513.403 | F11: 2.95 | G11: 15311 | H11: United Kingdom | I11: 5.9 | J11: 2010-12
A12: 536384 | B12: 22470 | C12: HEART OF WICKER LARGE | D12: 40 | E12: 40513.412 | F12: 2.55 | G12: 18074 | H12: United Kingdom | I12: 102 | J12: 2010-12
A13: 536388 | B13: 21363 | C13: HOME SMALL WOOD LETTERS | D13: 3 | E13: 40513.416 | F13: 4.95 | G13: 16250 | H13: United Kingdom | I13: 14.85 | J13: 2010-12
... A80: 536542 | B80: 85099C | C80: JUMBO BAG BAROQUE BLACK WHITE | D80: 20 | E80: 40513.591 | F80: 1.95 | G80: 16456 | H80: United Kingdom | I80: 39 | J80: 2010-12
A81: 536544 | B81: 21165 | C81: BEWARE OF THE CAT METAL SIGN | D81: 1 | E81: 40513.606 | F81: 4.21 | H81: United Kingdom | I81: 4.21 | J81: 2010-12
A82: 536544 | B82: 90071 | C82: RUBY GLASS CLUSTER EARRINGS | D82: 1 | E82: 40513.606 | F82: 1.26 | H82: United Kingdom | I82: 1.26 | J82: 2010-12
A83: 536544 | B83: 85135C | C83: RED DRAGONFLY HELICOPTER | D83: 1 | E83: 40513.606 | F83: 8.47 | H83: United Kingdom | I83: 8.47 | J83: 2010-12
A84: 536544 | B84: 22962 | C84: JAM JAR WITH PINK LID | D84: 4 | E84: 40513.606 | F84: 1.66 | H84: United Kingdom | I84: 6.64 | J84: 2010-12
A85: 536544 | B85: 85135B | C85: BLUE DRAGONFLY HELICOPTER | D85: 1 | E85: 40513.606 | F85: 8.47 | H85: United Kingdom | I85: 8.47 | J85: 2010-12
A86: 536544 | B86: 22945 | C86: CHRISTMAS METAL TAGS ASSORTED | D86: 1 | E86: 40513.606 | F86: 11.02 | H86: United Kingdom | I86: 11.02 | J86: 2010-12
A87: 536544 | B87: 22515 | C87: CHILDS GARDEN SPADE PINK | D87: 1 | E87: 40513.606 | F87: 4.21 | H87: United Kingdom | I87: 4.21 | J87: 2010-12
A88: 536544 | B88: 84580 | C88: MOUSE TOY WITH PINK T-SHIRT | D88: 1 | E88: 40513.606 | F88: 4.21 | H88: United Kingdom | I88: 4.21 | J88: 2010-12
A89: 536544 | B89: 22224 | C89: WHITE LOVEBIRD LANTERN | D89: 1 | E89: 40513.606 | F89: 5.91 | H89: United Kingdom | I89: 5.91 | J89: 2010-12
A90: 536544 | B90: 20685 | C90: DOORMAT RED RETROSPOT | D90: 1 | E90: 40513.606 | F90: 14.43 | H90: United Kingdom | I90: 14.43 | J90: 2010-12
A91: 536544 | B91: 72586 | C91: SET OF 6 HALLOWEEN GHOST T-LIGHTS | D91: 1 | E91: 40513.606 | F91: 0.85 | H91: United Kingdom | I91: 0.85 | J91: 2010-12
A92: 536544 | B92: 22130 | C92: PARTY CONE CHRISTMAS DECORATION | D92: 2 | E92: 40513.606 | F92: 8.47 | H92: United Kingdom | I92: 16.94 | J92: 2010-12
... A110: 536544 | B110: 20971 | C110: PINK BLUE FELT CRAFT TRINKET BOX | D110: 1 | E110: 40513.606 | F110: 2.51 | H110: United Kingdom | I110: 2.51 | J110: 2010-12
A111: 536557 | B111: 22730 | C111: ALARM CLOCK BAKELIKE IVORY | D111: 1 | E111: 40513.612 | F111: 3.75 | G111: 17841 | H111: United Kingdom | I111: 3.75 | J111: 2010-12
A112: 536557 | B112: 22794 | C112: SWEETHEART WIRE MAGAZINE RACK | D112: 1 | E112: 40513.612 | F112: 7.95 | G112: 17841 | H112: United Kingdom | I112: 7.95 | J112: 2010-12
A113: 536559 | B113: 51014A | C113: FEATHER PEN,HOT PINK | D113: 12 | E113: 40513.621 | F113: 0.85 | G113: 17873 | H113: United Kingdom | I113: 10.2 | J113: 2010-12
A114: 536561 | B114: 22750 | C114: FELTCRAFT PRINCESS LOLA DOLL | D114: 4 | E114: 40513.629 | F114: 3.75 | G114: 12921 | H114: United Kingdom | I114: 15 | J114: 2010-12
A115: 536569 | B115: 22496 | C115: SET OF 2 ROUND TINS DUTCH CHEESE | D115: 1 | E115: 40513.649 | F115: 2.95 | G115: 16274 | H115: United Kingdom | I115: 2.95 | J115: 2010-12
A116: 536569 | B116: 22659 | C116: LUNCH BOX I LOVE LONDON | D116: 1 | E116: 40513.649 | F116: 1.95 | G116: 16274 | H116: United Kingdom | I116: 1.95 | J116: 2010-12
A117: 536569 | B117: 21147 | C117: JINGLE BELLS TREE DECORATION | D117: 2 | E117: 40513.649 | F117: 2.1 | G117: 16274 | H117: United Kingdom | I117: 4.2 | J117: 2010-12
A118: 536570 | B118: 84836 | C118: ZINC METAL HEART DECORATION | D118: 12 | E118: 40513.649 | F118: 1.25 | G118: 14496 | H118: United Kingdom | I118: 15 | J118: 2010-12
A119: 536571 | B119: 21790 | C119: VINTAGE SNAP CARDS | D119: 12 | E119: 40513.651 | F119: 0.85 | G119: 14696 | H119: United Kingdom | I119: 10.2 | J119: 2010-12
A120: 536572 | B120: 21754 | C120: HOME BUILDING BLOCK WORD | D120: 6 | E120: 40513.653 | F120: 5.95 | G120: 16539 | H120: United Kingdom | I120: 35.7 | J120: 2010-12
A121: 536572 | B121: 22579 | C121: WOODEN TREE CHRISTMAS SCANDINAVIAN | D121: 24 | E121: 40513.653 | F121: 0.85 | G121: 16539 | H121: United Kingdom | I121: 20.4 | J121: 2010-12
A122: 536575 | B122: 22095 | C122: LADS ONLY TISSUE BOX | D122: 252 | E122: 40513.667 | F122: 1.25 | G122: 13777 | H122: United Kingdom | I122: 315 | J122: 2010-12
... A132: 536591 | B132: 85064 | C132: CREAM SWEETHEART LETTER RACK | D132: 2 | E132: 40513.707 | F132: 5.45 | G132: 14606 | H132: United Kingdom | I132: 10.9 | J132: 2010-12
A133: 536592 | B133: 21871 | C133: SAVE THE PLANET MUG | D133: 3 | E133: 40513.713 | F133: 3.36 | H133: United Kingdom | I133: 10.08 | J133: 2010-12
A134: 536592 | B134: 85114B | C134: IVORY ENCHANTED FOREST PLACEMAT | D134: 1 | E134: 40513.713 | F134: 3.36 | H134: United Kingdom | I134: 3.36 | J134: 2010-12
A135: 536592 | B135: 85132A | C135: CHARLIE + LOLA BISCUITS TINS | D135: 1 | E135: 40513.713 | F135: 8.47 | H135: United Kingdom | I135: 8.47 | J135: 2010-12
A136: 536592 | B136: 22694 | C136: WICKER STAR | D136: 1 | E136: 40513.713 | F136: 4.21 | H136: United Kingdom | I136: 4.21 | J136: 2010-12
A137: 536592 | B137: 21165 | C137: BEWARE OF THE CAT METAL SIGN | D137: 3 | E137: 40513.713 | F137: 4.21 | H137: United Kingdom | I137: 12.63 | J137: 2010-12
A138: 536592 | B138: 21544 | C138: SKULLS WATER TRANSFER TATTOOS | D138: 1 | E138: 40513.713 | F138: 1.66 | H138: United Kingdom | I138: 1.66 | J138: 2010-12
A139: 536592 | B139: 20973 | C139: 12 PENCIL SMALL TUBE WOODLAND | D139: 15 | E139: 40513.713 | F139: 1.28 | H139: United Kingdom | I139: 19.2 | J139: 2010-12
A140: 536592 | B140: 85015 | C140: SET OF 12 VINTAGE POSTCARD SET | D140: 2 | E140: 40513.713 | F140: 2.51 | H140: United Kingdom | I140: 5.02 | J140: 2010-12
A141: 536592 | B141: 21745 | C141: GAOLERS KEYS DECORATIVE GARDEN | D141: 1 | E141: 40513.713 | F141: 8.47 | H141: United Kingdom | I141: 8.47 | J141: 2010-12
A142: 536592 | B142: 20914 | C142: SET/5 RED RETROSPOT LID GLASS BOWLS | D142: 1 | E142: 40513.713 | F142: 5.91 | H142: United Kingdom | I142: 5.91 | J142: 2010-12
A143: 536592 | B143: 21889 | C143: WOODEN BOX OF DOMINOES | D143: 2 | E143: 40513.713 | F143: 2.51 | H143: United Kingdom | I143: 5.02 | J143: 2010-12
A144: 536592 | B144: 90166 | C144: PINK & WHITE ROSEBUD RING | D144: 1 | E144: 40513.713 | F144: 4.24 | H144: United Kingdom | I144: 4.24 | J144: 2010-12
... A161: 536592 | B161: 22916 | C161: HERB MARKER THYME | D161: 1 | E161: 40513.713 | F161: 1.66 | H161: United Kingdom | I161: 1.66 | J161: 2010-12
A162: 536595 | B162: 21137 | C162: BLACK RECORD COVER FRAME | D162: 60 | E162: 40513.725 | F162: 3.39 | G162: 13576 | H162: United Kingdom | I162: 203.4 | J162: 2010-12
A163: 536598 | B163: 22178 | C163: VICTORIAN GLASS HANGING T-LIGHT | D163: 24 | E163: 40514.325 | F163: 1.25 | G163: 13090 | H163: United Kingdom | I163: 30 | J163: 2010-12
A164: 536600 | B164: 84029E | C164: RED WOOLLY HOTTIE WHITE HEART. | D164: 6 | E164: 40514.356 | F164: 3.39 | G164: 17850 | H164: United Kingdom | I164: 20.34 | J164: 2010-12
A165: 536602 | B165: 85123A | C165: WHITE HANGING HEART T-LIGHT HOLDER | D165: 6 | E165: 40514.357 | F165: 2.55 | G165: 17850 | H165: United Kingdom | I165: 15.3 | J165: 2010-12
A166: 536604 | B166: 84970S | C166: HANGING HEART ZINC T-LIGHT HOLDER | D166: 12 | E166: 40514.363 | F166: 0.85 | G166: 14741 | H166: United Kingdom | I166: 10.2 | J166: 2010-12
A167: 536605 | B167: 21364 | C167: PEACE SMALL WOOD LETTERS | D167: 2 | E167: 40514.369 | F167: 6.75 | G167: 13715 | H167: United Kingdom | I167: 13.5 | J167: 2010-12
A168: 536607 | B168: 85123A | C168: WHITE HANGING HEART T-LIGHT HOLDER | D168: 6 | E168: 40514.395 | F168: 2.95 | G168: 17732 | H168: United Kingdom | I168: 17.7 | J168: 2010-12
A169: 536609 | B169: 84029G | C169: KNITTED UNION FLAG HOT WATER BOTTLE | D169: 6 | E169: 40514.403 | F169: 3.39 | G169: 17850 | H169: United Kingdom | I169: 20.34 | J169: 2010-12
A170: 536611 | B170: 21790 | C170: VINTAGE SNAP CARDS | D170: 12 | E170: 40514.405 | F170: 0.85 | G170: 15752 | H170: United Kingdom | I170: 10.2 | J170: 2010-12
A171: 536613 | B171: 22818 | C171: CARD CHRISTMAS VILLAGE | D171: 12 | E171: 40514.406 | F171: 0.42 | G171: 17855 | H171: United Kingdom | I171: 5.04 | J171: 2010-12
A172: 536613 | B172: 22544 | C172: MINI JIGSAW SPACEBOY | D172: 24 | E172: 40514.406 | F172: 0.42 | G172: 17855 | H172: United Kingdom | I172: 10.08 | J172: 2010-12
A173: 536613 | B173: 22652 | C173: TRAVEL SEWING KIT | D173: 10 | E173: 40514.406 | F173: 1.65 | G173: 17855 | H173: United Kingdom | I173: 16.5 | J173: 2010-12
... A218: 536754 | B218: 22335 | C218: HEART DECORATION PAINTED ZINC | D218: 10 | E218: 40514.59 | F218: 0.65 | G218: 14449 | H218: United Kingdom | I218: 6.5 | J218: 2010-12
A219: 536756 | B219: 22909 | C219: SET OF 20 VINTAGE CHRISTMAS NAPKINS | D219: 1 | E219: 40514.599 | F219: 0.85 | H219: United Kingdom | I219: 0.85 | J219: 2010-12
A220: 536756 | B220: 22325 | C220: MOBILE VINTAGE HEARTS | D220: 1 | E220: 40514.599 | F220: 4.95 | H220: United Kingdom | I220: 4.95 | J220: 2010-12
A221: 536759 | B221: 21745 | C221: GAOLERS KEYS DECORATIVE GARDEN | D221: 4 | E221: 40514.601 | F221: 3.75 | G221: 16781 | H221: United Kingdom | I221: 15 | J221: 2010-12
A222: 536759 | B222: 21781 | C222: MA CAMPAGNE CUTLERY BOX | D222: 1 | E222: 40514.601 | F222: 14.95 | G222: 16781 | H222: United Kingdom | I222: 14.95 | J222: 2010-12
A223: 536762 | B223: 21700 | C223: BIG DOUGHNUT FRIDGE MAGNETS | D223: 12 | E223: 40514.611 | F223: 0.85 | G223: 16186 | H223: United Kingdom | I223: 10.2 | J223: 2010-12
A224: 536777 | B224: 21500 | C224: PINK POLKADOT WRAP | D224: 25 | E224: 40514.625 | F224: 0.42 | G224: 15732 | H224: United Kingdom | I224: 10.5 | J224: 2010-12
A225: 536778 | B225: 15036 | C225: ASSORTED COLOURS SILK FAN | D225: 12 | E225: 40514.627 | F225: 0.75 | G225: 13138 | H225: United Kingdom | I225: 9 | J225: 2010-12
A226: 536782 | B226: 22198 | C226: LARGE POPCORN HOLDER | D226: 12 | E226: 40514.637 | F226: 1.65 | G226: 17567 | H226: United Kingdom | I226: 19.8 | J226: 2010-12
A227: 536782 | B227: 21668 | C227: RED STRIPE CERAMIC DRAWER KNOB | D227: 12 | E227: 40514.637 | F227: 1.25 | G227: 17567 | H227: United Kingdom | I227: 15 | J227: 2010-12
A228: 536783 | B228: 22533 | C228: MAGIC DRAWING SLATE BAKE A CAKE | D228: 24 | E228: 40514.638 | F228: 0.36 | G228: 15061 | H228: United Kingdom | I228: 8.64 | J228: 2010-12
A229: 536783 | B229: 21498 | C229: RED RETROSPOT WRAP | D229: 200 | E229: 40514.638 | F229: 0.34 | G229: 15061 | H229: United Kingdom | I229: 68 | J229: 2010-12
A230: 536785 | B230: 22423 | C230: REGENCY CAKESTAND 3 TIER | D230: 144 | E230: 40514.64 | F230: 10.95 | G230: 15061 | H230: United Kingdom | I230: 1576.8 | J230: 2010-12
A231: 536787 | B231: 84029E | C231: RED WOOLLY HOTTIE WHITE HEART. | D231: 6 | E231: 40514.642 | F231: 3.39 | G231: 17850 | H231: United Kingdom | I231: 20.34 | J231: 2010-12
A232: 536787 | B232: 22752 | C232: SET 7 BABUSHKA NESTING BOXES | D232: 2 | E232: 40514.642 | F232: 7.65 | G232: 17850 | H232: United Kingdom | I232: 15.3 | J232: 2010-12
... A237: 536798 | B237: 21901 | C237: KEY FOB , BACK DOOR | D237: 48 | E237: 40514.663 | F237: 0.65 | G237: 17838 | H237: United Kingdom | I237: 31.2 | J237: 2010-12
A238: 536801 | B238: 22111 | C238: SCOTTIE DOG HOT WATER BOTTLE | D238: 6 | E238: 40514.675 | F238: 4.95 | H238: United Kingdom | I238: 29.7 | J238: 2010-12
A239: 536800 | B239: 22716 | C239: CARD CIRCUS PARADE | D239: 12 | E239: 40514.675 | F239: 0.42 | G239: 14829 | H239: United Kingdom | I239: 5.04 | J239: 2010-12
A240: 536800 | B240: 22814 | C240: CARD PARTY GAMES | D240: 12 | E240: 40514.675 | F240: 0.42 | G240: 14829 | H240: United Kingdom | I240: 5.04 | J240: 2010-12
A241: 536801 | B241: 82599 | C241: FANNY'S REST STOPMETAL SIGN | D241: 12 | E241: 40514.675 | F241: 2.1 | H241: United Kingdom | I241: 25.2 | J241: 2010-12
A242: 536804 | B242: 22065 | C242: CHRISTMAS PUDDING TRINKET POT | D242: 10 | E242: 40514.69 | F242: 1.45 | G242: 14031 | H242: United Kingdom | I242: 14.5 | J242: 2010-12
A243: 536804 | B243: 22328 | C243: ROUND SNACK BOXES SET OF 4 FRUITS | D243: 6 | E243: 40514.69 | F243: 2.95 | G243: 14031 | H243: United Kingdom | I243: 17.7 | J243: 2010-12
A244: 536804 | B244: 22326 | C244: ROUND SNACK BOXES SET OF4 WOODLAND | D244: 6 | E244: 40514.69 | F244: 2.95 | G244: 14031 | H244: United Kingdom | I244: 17.7 | J244: 2010-12
A245: 536805 | B245: 37370 | C245: RETRO COFFEE MUGS ASSORTED | D245: 12 | E245: 40514.693 | F245: 1.25 | G245: 14775 | H245: United Kingdom | I245: 15 | J245: 2010-12
A246: 536806 | B246: 82581 | C246: TOILET METAL SIGN | D246: 12 | E246: 40514.696 | F246: 0.55 | G246: 12971 | H246: United Kingdom | I246: 6.6 | J246: 2010-12
A247: 536810 | B247: 21833 | C247: CAMOUFLAGE LED TORCH | D247: 204 | E247: 40514.701 | F247: 1.49 | G247: 15299 | H247: United Kingdom | I247: 303.96 | J247: 2010-12
A248: 536813 | B248: 22086 | C248: PAPER CHAIN KIT 50'S CHRISTMAS | D248: 6 | E248: 40514.708 | F248: 2.95 | G248: 15646 | H248: United Kingdom | I248: 17.7 | J248: 2010-12
A249: 536813 | B249: 22816 | C249: CARD MOTORBIKE SANTA | D249: 12 | E249: 40514.708 | F249: 0.42 | G249: 15646 | H249: United Kingdom | I249: 5.04 | J249: 2010-12
A250: 536813 | B250: 22089 | C250: PAPER BUNTING VINTAGE PAISLEY | D250: 6 | E250: 40514.708 | F250: 2.95 | G250: 15646 | H250: United Kingdom | I250: 17.7 | J250: 2010-12
A251: 536813 | B251: 37450 | C251: CERAMIC CAKE BOWL + HANGING CAKES | D251: 6 | E251: 40514.708 | F251: 2.95 | G251: 15646 | H251: United Kingdom | I251: 17.7 | J251: 2010-12
A252: 536823 | B252: 82494L | C252: WOODEN FRAME ANTIQUE WHITE | D252: 6 | E252: 40514.724 | F252: 2.95 | G252: 13011 | H252: United Kingdom | I252: 17.7 | J252: 2010-12
A253: 536833 | B253: 71053 | C253: WHITE METAL LANTERN | D253: 4 | E253: 40514.742 | F253: 3.75 | G253: 18239 | H253: United Kingdom | I253: 15 | J253: 2010-12
... A268: 536860 | B268: 22158 | C268: 3 HEARTS HANGING DECORATION RUSTIC | D268: 13 | E268: 40515.447 | F268: 2.95 | G268: 16905 | H268: United Kingdom | I268: 38.35 | J268: 2010-12
A269: 536862 | B269: 37370 | C269: RETRO COFFEE MUGS ASSORTED | D269: 2 | E269: 40515.467 | F269: 16.13 | H269: United Kingdom | I269: 32.26 | J269: 2010-12
A270: 536862 | B270: 22697 | C270: GREEN REGENCY TEACUP AND SAUCER | D270: 2 | E270: 40515.467 | F270: 5.91 | H270: United Kingdom | I270: 11.82 | J270: 2010-12
...

Sheet Data_Cancelled (full 9.251)
A1: InvoiceNo | B1: StockCode | C1: Description | D1: Quantity | E1: InvoiceDate | F1: UnitPrice | G1: CustomerID | H1: Country | I1: TotalPrice | J1: YearMonth
A2: C536379 | B2: D | C2: Discount | D2: -1 | E2: 40513.403 | F2: 27.5 | G2: 14527 | H2: United Kingdom | I2: -27.5 | J2: 2010-12
A3: C536383 | B3: 35004C | C3: SET OF 3 COLOURED FLYING DUCKS | D3: -1 | E3: 40513.409 | F3: 4.65 | G3: 15311 | H3: United Kingdom | I3: -4.65 | J3: 2010-12
A4: C536391 | B4: 22556 | C4: PLASTERS IN TIN CIRCUS PARADE | D4: -12 | E4: 40513.433 | F4: 1.65 | G4: 17548 | H4: United Kingdom | I4: -19.8 | J4: 2010-12
A5: C536391 | B5: 21984 | C5: PACK OF 12 PINK PAISLEY TISSUES | D5: -24 | E5: 40513.433 | F5: 0.29 | G5: 17548 | H5: United Kingdom | I5: -6.96 | J5: 2010-12
A6: C536391 | B6: 21983 | C6: PACK OF 12 BLUE PAISLEY TISSUES | D6: -24 | E6: 40513.433 | F6: 0.29 | G6: 17548 | H6: United Kingdom | I6: -6.96 | J6: 2010-12
A7: C536391 | B7: 21980 | C7: PACK OF 12 RED RETROSPOT TISSUES | D7: -24 | E7: 40513.433 | F7: 0.29 | G7: 17548 | H7: United Kingdom | I7: -6.96 | J7: 2010-12
A8: C536391 | B8: 21484 | C8: CHICK GREY HOT WATER BOTTLE | D8: -12 | E8: 40513.433 | F8: 3.45 | G8: 17548 | H8: United Kingdom | I8: -41.4 | J8: 2010-12
A9: C536391 | B9: 22557 | C9: PLASTERS IN TIN VINTAGE PAISLEY | D9: -12 | E9: 40513.433 | F9: 1.65 | G9: 17548 | H9: United Kingdom | I9: -19.8 | J9: 2010-12
A10: C536391 | B10: 22553 | C10: PLASTERS IN TIN SKULLS | D10: -24 | E10: 40513.433 | F10: 1.65 | G10: 17548 | H10: United Kingdom | I10: -39.6 | J10: 2010-12
A11: C536506 | B11: 22960 | C11: JAM MAKING SET WITH JARS | D11: -6 | E11: 40513.526 | F11: 4.25 | G11: 17897 | H11: United Kingdom | I11: -25.5 | J11: 2010-12
A12: C536543 | B12: 22632 | C12: HAND WARMER RED RETROSPOT | D12: -1 | E12: 40513.604 | F12: 2.1 | G12: 17841 | H12: United Kingdom | I12: -2.1 | J12: 2010-12
A13: C536543 | B13: 22355 | C13: CHARLOTTE BAG SUKI DESIGN | D13: -2 | E13: 40513.604 | F13: 0.85 | G13: 17841 | H13: United Kingdom | I13: -1.7 | J13: 2010-12
... A103: C537234 | B103: 22653 | C103: BUTTON BOX | D103: -20 | E103: 40518.403 | F103: 1.95 | G103: 16161 | H103: United Kingdom | I103: -39 | J103: 2010-12
A104: C537251 | B104: 22429 | C104: ENAMEL MEASURING JUG CREAM | D104: -2 | E104: 40518.448 | F104: 4.25 | H104: United Kingdom | I104: -8.5 | J104: 2010-12
A105: C537251 | B105: 22620 | C105: 4 TRADITIONAL SPINNING TOPS | D105: -8 | E105: 40518.448 | F105: 1.25 | H105: United Kingdom | I105: -10 | J105: 2010-12
A106: C537251 | B106: 21890 | C106: S/6 WOODEN SKITTLES IN COTTON BAG | D106: -2 | E106: 40518.448 | F106: 2.95 | H106: United Kingdom | I106: -5.9 | J106: 2010-12
A107: C537251 | B107: 22564 | C107: ALPHABET STENCIL CRAFT | D107: -5 | E107: 40518.448 | F107: 1.25 | H107: United Kingdom | I107: -6.25 | J107: 2010-12
A108: C537251 | B108: 21891 | C108: TRADITIONAL WOODEN SKIPPING ROPE | D108: -3 | E108: 40518.448 | F108: 1.25 | H108: United Kingdom | I108: -3.75 | J108: 2010-12
A109: C537251 | B109: 22747 | C109: POPPY'S PLAYHOUSE BATHROOM | D109: -6 | E109: 40518.448 | F109: 2.1 | H109: United Kingdom | I109: -12.6 | J109: 2010-12
A110: C537251 | B110: 22454 | C110: MEASURING TAPE BABUSHKA RED | D110: -8 | E110: 40518.448 | F110: 2.95 | H110: United Kingdom | I110: -23.6 | J110: 2010-12
A111: C537251 | B111: 22327 | C111: ROUND SNACK BOXES SET OF 4 SKULLS | D111: -4 | E111: 40518.448 | F111: 2.95 | H111: United Kingdom | I111: -11.8 | J111: 2010-12
A112: C537251 | B112: 21915 | C112: RED HARMONICA IN BOX | D112: -4 | E112: 40518.448 | F112: 1.25 | H112: United Kingdom | I112: -5 | J112: 2010-12
A113: C537251 | B113: 84347 | C113: ROTATING SILVER ANGELS T-LIGHT HLDR | D113: -9 | E113: 40518.448 | F113: 2.55 | H113: United Kingdom | I113: -22.95 | J113: 2010-12
A114: C537251 | B114: 22748 | C114: POPPY'S PLAYHOUSE KITCHEN | D114: -4 | E114: 40518.448 | F114: 2.1 | H114: United Kingdom | I114: -8.4 | J114: 2010-12
A115: C537251 | B115: 22943 | C115: CHRISTMAS LIGHTS 10 VINTAGE BAUBLES | D115: -6 | E115: 40518.448 | F115: 4.95 | H115: United Kingdom | I115: -29.7 | J115: 2010-12
... A123: C537251 | B123: 22466 | C123: FAIRY TALE COTTAGE NIGHTLIGHT | D123: -3 | E123: 40518.448 | F123: 1.95 | H123: United Kingdom | I123: -5.85 | J123: 2010-12
A124: C537314 | B124: 21349 | C124: IVY HEART WREATH | D124: -4 | E124: 40518.488 | F124: 6.75 | G124: 13497 | H124: United Kingdom | I124: -27 | J124: 2010-12
A125: C537320 | B125: 35400 | C125: WOODEN BOX ADVENT CALENDAR | D125: -1 | E125: 40518.491 | F125: 8.95 | G125: 14867 | H125: United Kingdom | I125: -8.95 | J125: 2010-12
A126: C537333 | B126: 22636 | C126: CHILDS BREAKFAST SET CIRCUS PARADE | D126: -4 | E126: 40518.5 | F126: 8.5 | G126: 12474 | H126: Germany | I126: -34 | J126: 2010-12
A127: C537373 | B127: 22423 | C127: REGENCY CAKESTAND 3 TIER | D127: -1 | E127: 40518.538 | F127: 12.75 | G127: 14487 | H127: United Kingdom | I127: -12.75 | J127: 2010-12
A128: C537379 | B128: 22865 | C128: HAND WARMER OWL DESIGN | D128: -10 | E128: 40518.55 | F128: 2.1 | G128: 15882 | H128: United Kingdom | I128: -21 | J128: 2010-12
A129: C537383 | B129: 21658 | C129: GLASS BEURRE DISH | D129: -1 | E129: 40518.553 | F129: 3.95 | G129: 16550 | H129: United Kingdom | I129: -3.95 | J129: 2010-12
A130: C537383 | B130: 22197 | C130: SMALL POPCORN HOLDER | D130: -1 | E130: 40518.553 | F130: 0.85 | G130: 16550 | H130: United Kingdom | I130: -0.85 | J130: 2010-12
A131: C537383 | B131: 22371 | C131: AIRLINE BAG VINTAGE TOKYO 78 | D131: -1 | E131: 40518.553 | F131: 4.25 | G131: 16550 | H131: United Kingdom | I131: -4.25 | J131: 2010-12
A132: C537398 | B132: 22430 | C132: ENAMEL WATERING CAN CREAM | D132: -1 | E132: 40518.599 | F132: 4.95 | G132: 15426 | H132: United Kingdom | I132: -4.95 | J132: 2010-12
A133: C537402 | B133: 22926 | C133: IVORY GIANT GARDEN THERMOMETER | D133: -4 | E133: 40518.613 | F133: 5.95 | G133: 15502 | H133: United Kingdom | I133: -23.8 | J133: 2010-12
A134: C537402 | B134: 22927 | C134: GREEN GIANT GARDEN THERMOMETER | D134: -4 | E134: 40518.613 | F134: 5.95 | G134: 15502 | H134: United Kingdom | I134: -23.8 | J134: 2010-12
A135: C537402 | B135: 22849 | C135: BREAD BIN DINER STYLE MINT | D135: -4 | E135: 40518.613 | F135: 14.95 | G135: 15502 | H135: United Kingdom | I135: -59.8 | J135: 2010-12
... A155: C537530 | B155: 22726 | C155: ALARM CLOCK BAKELIKE GREEN | D155: -2 | E155: 40519.491 | F155: 3.75 | G155: 13319 | H155: United Kingdom | I155: -7.5 | J155: 2010-12
A156: C537572 | B156: BANK CHARGES | C156: Bank Charges | D156: -1 | E156: 40519.5 | F156: 95.38 | H156: United Kingdom | I156: -95.38 | J156: 2010-12
A157: C537581 | B157: S | C157: SAMPLES | D157: -1 | E157: 40519.502 | F157: 12.95 | H157: United Kingdom | I157: -12.95 | J157: 2010-12
A158: C537581 | B158: S | C158: SAMPLES | D158: -1 | E158: 40519.502 | F158: 52 | H158: United Kingdom | I158: -52 | J158: 2010-12
A159: C537596 | B159: 22968 | C159: ROSE COTTAGE KEEPSAKE BOX | D159: -2 | E159: 40519.522 | F159: 9.95 | G159: 17954 | H159: United Kingdom | I159: -19.9 | J159: 2010-12
A160: C537597 | B160: D | C160: Discount | D160: -1 | E160: 40519.524 | F160: 281 | G160: 15498 | H160: United Kingdom | I160: -281 | J160: 2010-12
A161: C537600 | B161: AMAZONFEE | C161: AMAZON FEE | D161: -1 | E161: 40519.528 | F161: 1 | H161: United Kingdom | I161: -1 | J161: 2010-12
A162: C537602 | B162: 85099B | C162: JUMBO BAG RED RETROSPOT | D162: -1 | E162: 40519.531 | F162: 1.65 | G162: 17511 | H162: United Kingdom | I162: -1.65 | J162: 2010-12
A163: C537602 | B163: 21622 | C163: VINTAGE UNION JACK CUSHION COVER | D163: -1 | E163: 40519.531 | F163: 4.95 | G163: 17511 | H163: United Kingdom | I163: -4.95 | J163: 2010-12
A164: C537602 | B164: 22065 | C164: CHRISTMAS PUDDING TRINKET POT | D164: -1 | E164: 40519.531 | F164: 1.25 | G164: 17511 | H164: United Kingdom | I164: -1.25 | J164: 2010-12
A165: C537602 | B165: 22061 | C165: LARGE CAKE STAND HANGING STRAWBERY | D165: -1 | E165: 40519.531 | F165: 8.5 | G165: 17511 | H165: United Kingdom | I165: -8.5 | J165: 2010-12
A166: C537602 | B166: 22654 | C166: DELUXE SEWING KIT | D166: -1 | E166: 40519.531 | F166: 4.95 | G166: 17511 | H166: United Kingdom | I166: -4.95 | J166: 2010-12
A167: C537602 | B167: 85123A | C167: WHITE HANGING HEART T-LIGHT HOLDER | D167: -1 | E167: 40519.531 | F167: 2.55 | G167: 17511 | H167: United Kingdom | I167: -2.55 | J167: 2010-12
A168: C537602 | B168: 22665 | C168: RECIPE BOX BLUE SKETCHBOOK DESIGN | D168: -1 | E168: 40519.531 | F168: 2.95 | G168: 17511 | H168: United Kingdom | I168: -2.95 | J168: 2010-12
A169: C537602 | B169: 22197 | C169: SMALL POPCORN HOLDER | D169: -1 | E169: 40519.531 | F169: 0.72 | G169: 17511 | H169: United Kingdom | I169: -0.72 | J169: 2010-12
A170: C537602 | B170: 22659 | C170: LUNCH BOX I LOVE LONDON | D170: -4 | E170: 40519.531 | F170: 1.65 | G170: 17511 | H170: United Kingdom | I170: -6.6 | J170: 2010-12
A171: C537602 | B171: 22169 | C171: FAMILY ALBUM WHITE PICTURE FRAME | D171: -1 | E171: 40519.531 | F171: 7.65 | G171: 17511 | H171: United Kingdom | I171: -7.65 | J171: 2010-12
A172: C537602 | B172: 21843 | C172: RED RETROSPOT CAKE STAND | D172: -1 | E172: 40519.531 | F172: 9.95 | G172: 17511 | H172: United Kingdom | I172: -9.95 | J172: 2010-12
A173: C537602 | B173: 22423 | C173: REGENCY CAKESTAND 3 TIER | D173: -2 | E173: 40519.531 | F173: 10.95 | G173: 17511 | H173: United Kingdom | I173: -21.9 | J173: 2010-12
... A175: C537602 | B175: 22198 | C175: LARGE POPCORN HOLDER | D175: -1 | E175: 40519.531 | F175: 1.45 | G175: 17511 | H175: United Kingdom | I175: -1.45 | J175: 2010-12
A176: C537610 | B176: M | C176: Manual | D176: -1 | E176: 40519.558 | F176: 631.31 | H176: United Kingdom | I176: -631.31 | J176: 2010-12
A177: C537611 | B177: 22865 | C177: HAND WARMER OWL DESIGN | D177: -36 | E177: 40519.559 | F177: 2.1 | G177: 17675 | H177: United Kingdom | I177: -75.6 | J177: 2010-12
A178: C537613 | B178: M | C178: Manual | D178: -1 | E178: 40519.561 | F178: 313.78 | H178: United Kingdom | I178: -313.78 | J178: 2010-12
A179: C537630 | B179: AMAZONFEE | C179: AMAZON FEE | D179: -1 | E179: 40519.628 | F179: 13541.33 | H179: United Kingdom | I179: -13541.33 | J179: 2010-12
A180: C537644 | B180: AMAZONFEE | C180: AMAZON FEE | D180: -1 | E180: 40519.649 | F180: 13474.79 | H180: United Kingdom | I180: -13474.79 | J180: 2010-12
A181: C537647 | B181: AMAZONFEE | C181: AMAZON FEE | D181: -1 | E181: 40519.653 | F181: 5519.25 | H181: United Kingdom | I181: -5519.25 | J181: 2010-12
A182: C537651 | B182: AMAZONFEE | C182: AMAZON FEE | D182: -1 | E182: 40519.659 | F182: 13541.33 | H182: United Kingdom | I182: -13541.33 | J182: 2010-12
A183: C537652 | B183: AMAZONFEE | C183: AMAZON FEE | D183: -1 | E183: 40519.66 | F183: 6706.71 | H183: United Kingdom | I183: -6706.71 | J183: 2010-12
A184: C537656 | B184: 21258 | C184: VICTORIAN SEWING BOX LARGE | D184: -12 | E184: 40519.681 | F184: 10.95 | G184: 15100 | H184: United Kingdom | I184: -131.4 | J184: 2010-12
A185: C537677 | B185: 21166 | C185: COOK WITH WINE METAL SIGN | D185: -1 | E185: 40520.413 | F185: 1.95 | G185: 14796 | H185: United Kingdom | I185: -1.95 | J185: 2010-12
A186: C537684 | B186: 22301 | C186: COFFEE MUG CAT + BIRD DESIGN | D186: -1 | E186: 40520.429 | F186: 2.55 | G186: 14901 | H186: United Kingdom | I186: -2.55 | J186: 2010-12
A187: C537684 | B187: 22730 | C187: ALARM CLOCK BAKELIKE IVORY | D187: -1 | E187: 40520.429 | F187: 3.75 | G187: 14901 | H187: United Kingdom | I187: -3.75 | J187: 2010-12
A188: C537746 | B188: 22156 | C188: HEART DECORATION WITH PEARLS | D188: -1 | E188: 40520.46 | F188: 0.85 | G188: 15021 | H188: United Kingdom | I188: -0.85 | J188: 2010-12
A189: C537746 | B189: 21558 | C189: SKULL LUNCH BOX WITH CUTLERY | D189: -1 | E189: 40520.46 | F189: 2.55 | G189: 15021 | H189: United Kingdom | I189: -2.55 | J189: 2010-12
A190: C537746 | B190: 71477 | C190: COLOUR GLASS. STAR T-LIGHT HOLDER | D190: -1 | E190: 40520.46 | F190: 3.25 | G190: 15021 | H190: United Kingdom | I190: -3.25 | J190: 2010-12
A191: C537756 | B191: 21914 | C191: BLUE HARMONICA IN BOX | D191: -24 | E191: 40520.481 | F191: 1.25 | G191: 14952 | H191: United Kingdom | I191: -30 | J191: 2010-12
A192: C537756 | B192: 84949 | C192: SILVER HANGING T-LIGHT HOLDER | D192: -8 | E192: 40520.481 | F192: 1.65 | G192: 14952 | H192: United Kingdom | I192: -13.2 | J192: 2010-12
A193: C537756 | B193: 21275 | C193: ZINC TOP 2 DOOR WOODEN SHELF | D193: -4 | E193: 40520.481 | F193: 14.95 | G193: 14952 | H193: United Kingdom | I193: -59.8 | J193: 2010-12
A194: C537763 | B194: 85068 | C194: CREAM SWEETHEART SHELF + HOOKS | D194: -1 | E194: 40520.502 | F194: 7.95 | G194: 16713 | H194: United Kingdom | I194: -7.95 | J194: 2010-12
A195: C537788 | B195: 90062 | C195: CARNIVAL BRACELET | D195: -1 | E195: 40520.534 | F195: 12.75 | G195: 15916 | H195: United Kingdom | I195: -12.75 | J195: 2010-12
... A330: C538164 | B330: 35004B | C330: SET OF 3 BLACK FLYING DUCKS | D330: -1 | E330: 40521.731 | F330: 1.95 | G330: 14031 | H330: United Kingdom | I330: -1.95 | J330: 2010-12
A331: C538189 | B331: M | C331: Manual | D331: -1 | E331: 40522.441 | F331: 133.08 | H331: United Kingdom | I331: -133.08 | J331: 2010-12
A332: C538314 | B332: 22586 | C332: FELTCRAFT HAIRBAND PINK AND BLUE | D332: -47 | E332: 40522.578 | F332: 0.85 | G332: 15514 | H332: United Kingdom | I332: -39.95 | J332: 2010-12
A333: C538341 | B333: 84380 | C333: SET OF 3 BUTTERFLY COOKIE CUTTERS | D333: -1 | E333: 40522.585 | F333: 1.25 | G333: 15514 | H333: United Kingdom | I333: -1.25 | J333: 2010-12
A334: C538341 | B334: 22988 | C334: SOLDIERS EGG CUP | D334: -36 | E334: 40522.585 | F334: 1.25 | G334: 15514 | H334: United Kingdom | I334: -45 | J334: 2010-12
A335: C538341 | B335: 22988 | C335: SOLDIERS EGG CUP | D335: -12 | E335: 40522.585 | F335: 1.25 | G335: 15514 | H335: United Kingdom | I335: -15 | J335: 2010-12
A336: C538341 | B336: 22976 | C336: CIRCUS PARADE CHILDRENS EGG CUP | D336: -12 | E336: 40522.585 | F336: 1.25 | G336: 15514 | H336: United Kingdom | I336: -15 | J336: 2010-12
A337: C538341 | B337: 22973 | C337: CHILDREN'S CIRCUS PARADE MUG | D337: -18 | E337: 40522.585 | F337: 1.65 | G337: 15514 | H337: United Kingdom | I337: -29.7 | J337: 2010-12
A338: C538341 | B338: 22943 | C338: CHRISTMAS LIGHTS 10 VINTAGE BAUBLES | D338: -6 | E338: 40522.585 | F338: 4.95 | G338: 15514 | H338: United Kingdom | I338: -29.7 | J338: 2010-12
A339: C538341 | B339: 22752 | C339: SET 7 BABUSHKA NESTING BOXES | D339: -96 | E339: 40522.585 | F339: 7.65 | G339: 15514 | H339: United Kingdom | I339: -734.4 | J339: 2010-12
A340: C538341 | B340: 22730 | C340: ALARM CLOCK BAKELIKE IVORY | D340: -1 | E340: 40522.585 | F340: 3.75 | G340: 15514 | H340: United Kingdom | I340: -3.75 | J340: 2010-12
A341: C538341 | B341: 22729 | C341: ALARM CLOCK BAKELIKE ORANGE | D341: -4 | E341: 40522.585 | F341: 3.75 | G341: 15514 | H341: United Kingdom | I341: -15 | J341: 2010-12
A342: C538341 | B342: 22729 | C342: ALARM CLOCK BAKELIKE ORANGE | D342: -1 | E342: 40522.585 | F342: 3.75 | G342: 15514 | H342: United Kingdom | I342: -3.75 | J342: 2010-12
A343: C538341 | B343: 22728 | C343: ALARM CLOCK BAKELIKE PINK | D343: -1 | E343: 40522.585 | F343: 3.75 | G343: 15514 | H343: United Kingdom | I343: -3.75 | J343: 2010-12
... A420: C538670 | B420: 22114 | C420: HOT WATER BOTTLE TEA AND SYMPATHY | D420: -4 | E420: 40525.68 | F420: 3.95 | G420: 13448 | H420: United Kingdom | I420: -15.8 | J420: 2010-12
A421: C538680 | B421: BANK CHARGES | C421: Bank Charges | D421: -1 | E421: 40525.715 | F421: 966.92 | H421: United Kingdom | I421: -966.92 | J421: 2010-12
A422: C538681 | B422: M | C422: Manual | D422: -1 | E422: 40525.717 | F422: 316.3 | H422: United Kingdom | I422: -316.3 | J422: 2010-12
A423: C538682 | B423: M | C423: Manual | D423: -1 | E423: 40525.718 | F423: 1130.9 | H423: United Kingdom | I423: -1130.9 | J423: 2010-12
A424: C538684 | B424: 21258 | C424: VICTORIAN SEWING BOX LARGE | D424: -1 | E424: 40526.393 | F424: 12.75 | G424: 16161 | H424: United Kingdom | I424: -12.75 | J424: 2010-12
A425: C538684 | B425: 22946 | C425: WOODEN ADVENT CALENDAR CREAM | D425: -1 | E425: 40526.393 | F425: 16.95 | G425: 16161 | H425: United Kingdom | I425: -16.95 | J425: 2010-12
A426: C538684 | B426: 22470 | C426: HEART OF WICKER LARGE | D426: -1 | E426: 40526.393 | F426: 2.95 | G426: 16161 | H426: United Kingdom | I426: -2.95 | J426: 2010-12
...

Sheet Pivot_Bulanan
B2: REVENUE & ORDER PER BULAN
B3: Revenue/Order/Cancelled dihitung seluruh data (bukan sample) - lihat catatan metodologi di sheet Ringkasan.
B5: Bulan | C5: Revenue (GBP) | D5: Jumlah Order (distinct) | E5: AOV (GBP, formula) | F5: Baris Cancelled | G5: Revenue Hilang (Cancelled)
B6: 2010-12 | C6: 775714.95 | D6: 1550 | E6: =C6/D6 -> 500.46126 | F6: 719 | G6: 74729.12
B7: 2011-01 | C7: 670439.46 | D7: 1081 | E7: =C7/D7 -> 620.20302 | F7: 700 | G7: 131363.05
B8: 2011-02 | C8: 507866.54 | D8: 1093 | E8: =C8/D8 -> 464.65374 | F8: 470 | G8: 25519.15
B9: 2011-03 | C9: 689841.84 | D9: 1440 | E9: =C9/D9 -> 479.05683 | F9: 696 | G9: 34201.28
B10: 2011-04 | C10: 515499.66 | D10: 1236 | E10: =C10/D10 -> 417.07092 | F10: 558 | G10: 44600.65
B11: 2011-05 | C11: 740036.33 | D11: 1668 | E11: =C11/D11 -> 443.66686 | F11: 621 | G11: 47202.51
B12: 2011-06 | C12: 737683.99 | D12: 1525 | E12: =C12/D12 -> 483.72721 | F12: 709 | G12: 70569.78
B13: 2011-07 | C13: 688252.67 | D13: 1452 | E13: =C13/D13 -> 474.00322 | F13: 684 | G13: 37919.13
B14: 2011-08 | C14: 735370.22 | D14: 1340 | E14: =C14/D14 -> 548.78375 | F14: 667 | G14: 54330.8
B15: 2011-09 | C15: 1028345.4 | D15: 1818 | E15: =C15/D15 -> 565.64652 | F15: 801 | G15: 38838.51
B16: 2011-10 | C16: 1103364 | D16: 2006 | E16: =C16/D16 -> 550.03189 | F16: 1194 | G16: 81895.5
B17: 2011-11 | C17: 1452116 | D17: 2751 | E17: =C17/D17 -> 527.85023 | F17: 1073 | G17: 47720.98
B18: 2011-12 | C18: 614499.25 | D18: 816 | E18: =C18/D18 -> 753.06281 | F18: 359 | G18: 205089.27
B20: Catatan: Des 2011 hanya sampai tanggal 9 (data tidak penuh sebulan) - jangan dibandingkan apple-to-apple dgn bulan lain.

Sheet Pivot_Negara
B2: REVENUE PER NEGARA (diurutkan tertinggi)
B4: Negara | C4: Revenue (GBP) | D4: Jumlah Baris Transaksi | E4: % dari Total Revenue (formula)
B5: United Kingdom | C5: 8736254.6 | D5: 478905 | E5: =C5/'Ringkasan & Insight'!$D$7 -> 0.85156729
B6: Netherlands | C6: 283889.34 | D6: 2322 | E6: =C6/'Ringkasan & Insight'!$D$7 -> 0.027672142
B7: EIRE | C7: 270850.86 | D7: 7768 | E7: =C7/'Ringkasan & Insight'!$D$7 -> 0.026401215
B8: Germany | C8: 205381.15 | D8: 8643 | E8: =C8/'Ringkasan & Insight'!$D$7 -> 0.020019548
B9: France | C9: 184493 | D9: 8085 | E9: =C9/'Ringkasan & Insight'!$D$7 -> 0.017983474
B10: Australia | C10: 138103.81 | D10: 1180 | E10: =C10/'Ringkasan & Insight'!$D$7 -> 0.013461683
B11: Spain | C11: 55706.56 | D11: 2417 | E11: =C11/'Ringkasan & Insight'!$D$7 -> 0.0054300025
B12: Switzerland | C12: 53065.6 | D12: 1927 | E12: =C12/'Ringkasan & Insight'!$D$7 -> 0.0051725747
B13: Japan | C13: 37416.37 | D13: 321 | E13: =C13/'Ringkasan & Insight'!$D$7 -> 0.0036471644
B14: Belgium | C14: 36927.34 | D14: 1935 | E14: =C14/'Ringkasan & Insight'!$D$7 -> 0.0035994962
B15: Sweden | C15: 36828.83 | D15: 427 | E15: =C15/'Ringkasan & Insight'!$D$7 -> 0.0035898939
B16: Norway | C16: 32454.64 | D16: 1048 | E16: =C16/'Ringkasan & Insight'!$D$7 -> 0.0031635193
... B42: Saudi Arabia | C42: 145.92 | D42: 9 | E42: =C42/'Ringkasan & Insight'!$D$7 -> 1.4223567e-05

Sheet Pivot_Produk
B2: TOP 15 PRODUK BY REVENUE
B3: PERHATIAN: Rank #2 (23843) dipengaruhi 1 transaksi outlier ~80.995 unit dalam 1 invoice - lihat sheet Ringkasan.
B5: Rank | C5: StockCode | D5: Description | E5: Revenue (GBP) | F5: Qty Terjual
B6: 1 | C6: 22423 | D6: REGENCY CAKESTAND 3 TIER | E6: 174156.54 | F6: 13851
B7: 2 | C7: 23843 | D7: PAPER CRAFT , LITTLE BIRDIE | E7: 168469.6 | F7: 80995
B8: 3 | C8: 85123A | D8: WHITE HANGING HEART T-LIGHT HOLDER | E8: 104284.24 | F8: 37641
B9: 4 | C9: 47566 | D9: PARTY BUNTING | E9: 99445.23 | F9: 18283
B10: 5 | C10: 85099B | D10: JUMBO BAG RED RETROSPOT | E10: 94159.81 | F10: 48371
B11: 6 | C11: 23166 | D11: MEDIUM CERAMIC TOP STORAGE JAR | E11: 81700.92 | F11: 78033
B12: 7 | C12: 23084 | D12: RABBIT NIGHT LIGHT | E12: 66870.03 | F12: 30739
B13: 8 | C13: 22086 | D13: PAPER CHAIN KIT 50'S CHRISTMAS | E13: 64875.59 | F13: 19329
B14: 9 | C14: 84879 | D14: ASSORTED COLOUR BIRD ORNAMENT | E14: 58927.62 | F14: 36362
B15: 10 | C15: 79321 | D15: CHILLI LIGHTS | E15: 54096.36 | F15: 10302
B16: 11 | C16: 23298 | D16: SPOTTY BUNTING | E16: 42513.48 | F16: 8466
B17: 12 | C17: 22386 | D17: JUMBO BAG PINK POLKADOT | E17: 42401.01 | F17: 21448
... B20: 15 | C20: 23284 | D20: DOORMAT KEEP CALM AND COME IN | E20: 38133.64 | F20: 5487

Sheet Pivot_Customer
B2: TOP 15 CUSTOMER BY REVENUE (RFM)
B3: Monetary/Frequency/Recency dihitung Python atas seluruh 522.571 baris (exclude CustomerID kosong).
B5: Rank | C5: CustomerID | D5: Negara | E5: Monetary/Revenue (GBP) | F5: Frequency (order) | G5: Recency (hari)
B6: 1 | C6: 14646 | D6: Netherlands | E6: 279138.02 | F6: 72 | G6: 1
B7: 2 | C7: 18102 | D7: United Kingdom | E7: 259657.3 | F7: 60 | G7: 0
B8: 3 | C8: 17450 | D8: United Kingdom | E8: 194390.79 | F8: 46 | G8: 7
B9: 4 | C9: 16446 | D9: United Kingdom | E9: 168472.5 | F9: 2 | G9: 0
B10: 5 | C10: 14911 | D10: EIRE | E10: 136161.83 | F10: 198 | G10: 0
B11: 6 | C11: 12415 | D11: Australia | E11: 124564.53 | F11: 20 | G11: 23
B12: 7 | C12: 14156 | D12: EIRE | E12: 116560.08 | F12: 54 | G12: 9
B13: 8 | C13: 17511 | D13: United Kingdom | E13: 91062.38 | F13: 31 | G13: 2
B14: 9 | C14: 12346 | D14: United Kingdom | E14: 77183.6 | F14: 1 | G14: 325
B15: 10 | C15: 16029 | D15: United Kingdom | E15: 72708.09 | F15: 62 | G15: 38
B16: 11 | C16: 16684 | D16: United Kingdom | E16: 66653.56 | F16: 28 | G16: 3
B17: 12 | C17: 13694 | D17: United Kingdom | E17: 65039.62 | F17: 50 | G17: 3
... B20: 15 | C20: 17949 | D20: United Kingdom | E20: 58030.48 | F20: 44 | G20: 0
B23: ANALISIS PARETO (dihitung Python, seluruh 4334 customer)
B24: Top 20% customer (866 orang) menyumbang 74.6% total revenue
B25: Hanya 1133 customer (26.1% dari total) sudah menyumbang 80% revenue

Sheet Pola_Waktu
B2: POLA WAKTU TRANSAKSI (Jam & Hari)
B4: Revenue per Jam
B5: Jam | C5: Revenue (GBP)
B6: 0 | C6: 0
B7: 1 | C7: 0
B8: 2 | C8: 0
B9: 3 | C9: 0
B10: 4 | C10: 0
B11: 5 | C11: 0
B12: 6 | C12: 4.25
B13: 7 | C13: 30469.21
B14: 8 | C14: 279297.68
B15: 9 | C15: 955760.16
B16: 10 | C16: 1401791.4
B17: 11 | C17: 1196812.6
... B29: 23 | C29: 0
B32: Revenue per Hari (1=Senin ... 7=Minggu)
B33: Hari | C33: Revenue (GBP)
B34: 1 - Senin | C34: 1683049.6
B35: 2 - Selasa | C35: 2085115.3
B36: 3 - Rabu | C36: 1782498.9
B37: 4 - Kamis | C37: 2131755.6
B38: 5 - Jumat | C38: 1778299.3
B39: 6 - Sabtu | C39: 0
B40: 7 - Minggu | C40: 798311.5
B42: Catatan: tidak ada transaksi hari Sabtu sama sekali di dataset ini (kemungkinan toko/gudang tutup).
